mamsi/__init__.py
mamsi/mamsi_pls.py
mamsi/mamsi_struct_search.py
mamsi/Data/Adducts/all_adducts_neg.csv
mamsi/Data/Adducts/all_adducts_pos.csv
mamsi/Data/Adducts/common_adducts_neg.csv
mamsi/Data/Adducts/common_adducts_pos.csv
mamsi/Data/ROI/HPOS_ROI_V_3_2_1.csv
mamsi/Data/ROI/LNEG_ROI_V_5_1_1.csv
mamsi/Data/ROI/LPOS_ROI_V_5_1_2.csv
mamsi/Data/ROI/RNEG_ROI_V_3_2_0.csv
mamsi/Data/ROI/RPOS_ROI_V_3_2_0.csv
mamsi-1.0.5.dist-info/METADATA
mamsi-1.0.5.dist-info/WHEEL
mamsi-1.0.5.dist-info/top_level.txt
mamsi-1.0.5.dist-info/RECORD
